MANIFEST.in
README.md
flask_crossdomain.py
setup.py
Flask_Crossdomain2.egg-info/PKG-INFO
Flask_Crossdomain2.egg-info/SOURCES.txt
Flask_Crossdomain2.egg-info/dependency_links.txt
Flask_Crossdomain2.egg-info/requires.txt
Flask_Crossdomain2.egg-info/top_level.txt