Metadata-Version: 1.1
Name: Flask-Crossdomain2
Version: 0.1.0
Summary: Module for enabling cross-site/cross-origin HTTP requests on Flask app endpoints.
Home-page: http://github.com/onenameio/flask-crossdomain
Author: Onename
Author-email: hello@onename.com
License: MIT
Platform: UNKNOWN
Classifier: Development Status :: 5 - Production/Stable
Classifier: Intended Audience :: Developers
Classifier: License :: OSI Approved :: MIT License
Classifier: Natural Language :: English
Classifier: Operating System :: OS Independent
Classifier: Programming Language :: Python :: 2
Classifier: Programming Language :: Python :: 3
Classifier: Topic :: Software Development :: Libraries :: Python Modules
